pytermx/__init__.py
pytermx/pytermx.py
pytermx-1.1.0.dist-info/LICENCE.md
pytermx-1.1.0.dist-info/METADATA
pytermx-1.1.0.dist-info/WHEEL
pytermx-1.1.0.dist-info/top_level.txt
pytermx-1.1.0.dist-info/RECORD
