Metadata-Version: 2.1
Name: pytermx
Version: 1.1.0
Summary: A python terminal decors package
Author: Sekateur
Author-email: akamecanic+seka@email.com
License: MIT
License-File: LICENCE.md
